MANIFEST.in
README.md
requirements.txt
setup.py
tagg/__init__.py
tagg/autotag.py
tagg/cli.py
tagg/default_defs.json
tagg/github.py
tagg.egg-info/PKG-INFO
tagg.egg-info/SOURCES.txt
tagg.egg-info/dependency_links.txt
tagg.egg-info/entry_points.txt
tagg.egg-info/requires.txt
tagg.egg-info/top_level.txt