Metadata-Version: 1.0
Name: tagg
Version: 0.1.2
Summary: CLI tool for tag-github project
Home-page: https://github.com/porter-io/tagg-python
Author: porter.io
Author-email: opensource@porter.io
License: UNKNOWN
Platform: UNKNOWN
